best/__init__.py
best/integration/__init__.py
best/unit/__init__.py
best/unit/conftest.py
best/unit/test_glue_session.py
best/unit/test_glue_session_demo.py
best/unit/test_session_apis.py
botocore3-119.4.6.dist-info/LICENSE.txt
botocore3-119.4.6.dist-info/METADATA
botocore3-119.4.6.dist-info/WHEEL
botocore3-119.4.6.dist-info/top_level.txt
botocore3-119.4.6.dist-info/RECORD
